ppg_log/__init__.py
ppg_log/metrics.py
ppg_log/parser.py
ppg_log-0.1.0.dist-info/LICENSE
ppg_log-0.1.0.dist-info/WHEEL
ppg_log-0.1.0.dist-info/METADATA
ppg_log-0.1.0.dist-info/RECORD
