Metadata-Version: 2.1
Name: ppg-log
Version: 0.1.0
Summary: Helper Tools for PPG FlySight Flight Log Management
Home-page: https://github.com/sco1/
Author: sco1
Author-email: sco1.git@gmail.com
Requires-Python: >=3.9,<4.0
Classifier: Development Status :: 4 - Beta
Classifier: Intended Audience :: Developers
Classifier: License :: OSI Approved :: MIT License
Classifier: Operating System :: OS Independent
Classifier: Programming Language :: Python :: 3
Classifier: Programming Language :: Python :: 3 :: Only
Classifier: Programming Language :: Python :: 3.10
Classifier: Programming Language :: Python :: 3.9
Classifier: Topic :: Scientific/Engineering
Classifier: Typing :: Typed
Requires-Dist: kaleido (>=0.2,<0.3,!=0.2.1.post1)
Requires-Dist: pandas (>=1.4,<2.0)
Requires-Dist: plotly (>=5.8,<6.0)
Requires-Dist: rich (>=12.4,<13.0)
Project-URL: Repository, https://github.com/sco1/ppg-log
